hackebds/ESH.py
hackebds/__init__.py
hackebds/aarch64.py
hackebds/arm.py
hackebds/backdoor_encode.py
hackebds/cve_info.py
hackebds/exp_database.py
hackebds/extract_shellcode.py
hackebds/hackebds_cmd.py
hackebds/hackebds_script.py
hackebds/mips.py
hackebds/mips32n.py
hackebds/model_choise.py
hackebds/my_package.py
hackebds/power_bind_shell.py
hackebds/power_reverse_shell.py
hackebds/powerpc_info.py
hackebds/sparc32.py
hackebds/sparc64.py
hackebds-0.3.8.data/data/README.md
hackebds-0.3.8.dist-info/DESCRIPTION.rst
hackebds-0.3.8.dist-info/METADATA
hackebds-0.3.8.dist-info/RECORD
hackebds-0.3.8.dist-info/WHEEL
hackebds-0.3.8.dist-info/entry_points.txt
hackebds-0.3.8.dist-info/metadata.json
hackebds-0.3.8.dist-info/top_level.txt
