Metadata-Version: 2.0
Name: hackebds
Version: 0.3.8
Summary: This tool is used for backdoor,shellcode generation,Information retrieval and POC generation for various architecture devices
Home-page: https://github.com/doudoudedi/hackEmbedded
Author: doudoudedi
Author-email: doudoudedi233@gmail.com
License: GPL-3.0
Platform: UNKNOWN
Requires-Python: >=3
Requires-Dist: colorama
Requires-Dist: fuzzywuzzy
Requires-Dist: mako
Requires-Dist: multidict
Requires-Dist: pwn
Requires-Dist: pwntools
Requires-Dist: pygments
Requires-Dist: requests
